jsonpp/__init__.py
jsonpp/command_line.py
jsonpp/jsonpp.py
jsonpp-0.0.1.dist-info/LICENSE
jsonpp-0.0.1.dist-info/METADATA
jsonpp-0.0.1.dist-info/WHEEL
jsonpp-0.0.1.dist-info/entry_points.txt
jsonpp-0.0.1.dist-info/top_level.txt
jsonpp-0.0.1.dist-info/RECORD
