Metadata-Version: 2.1
Name: jsonpp
Version: 0.0.1
Summary: JSON prettyprint in commandline
Home-page: https://github.com/sahil865gupta/jsonpp
Author: Sahil Gupta
Author-email: sahil865gupta@gmail.com
License: MIT
Keywords: command-line,pretty-print,colorful
Platform: UNKNOWN
Requires-Dist: Pygments (==2.5.2)
